Metadata-Version: 2.1
Name: textscribe
Version: 0.0.2
Summary: Easily Structuring Data
Home-page: 
Author: Hunter Thomas
Author-email: waidai2027@gmail.com
License: MIT
Keywords: Structure data
Classifier: Development Status :: 5 - Production/Stable
Classifier: Intended Audience :: Education
Classifier: Operating System :: Microsoft :: Windows :: Windows 10
Classifier: License :: OSI Approved :: MIT License
Classifier: Programming Language :: Python :: 3
Requires-Python: >=3.7
License-File: LICENSE
